README.md
setup.py
invoke_cptasklib/__init__.py
invoke_cptasklib/main.py
invoke_cptasklib.egg-info/PKG-INFO
invoke_cptasklib.egg-info/SOURCES.txt
invoke_cptasklib.egg-info/dependency_links.txt
invoke_cptasklib.egg-info/entry_points.txt
invoke_cptasklib.egg-info/not-zip-safe
invoke_cptasklib.egg-info/requires.txt
invoke_cptasklib.egg-info/top_level.txt
invoke_cptasklib/tasks/__init__.py
invoke_cptasklib/tasks/file_util.py
invoke_cptasklib/tasks/github.py
invoke_cptasklib/tasks/util.py