Metadata-Version: 1.0
Name: invoke-cptasklib
Version: 0.1.2
Summary: Task modules for invoke
Home-page: https://github.com/plockc/invoke-cptasklib
Author: Chris Plock
Author-email: UNKNOWN
License: Unlicense
Platform: UNKNOWN
